{
  "alola": {
    "reading": "ア(ロー)↑ラ",
    "meaning": "こんにちは",
    "etymology": "・ポケモンSM アローラ地方のあいさつ「アローラ」より",
    "examples": [
      {
        "kapu": "alola e siali!",
        "japanese": "こんにちは、しゃりー!"
      },
      {
        "kapu": "e malil si, alola!",
        "japanese": "マリルさん、こんにちは！"
      }
    ],
    "notes": "・基本的にいつでも使えるが、昼に使うことが多い。"
  },
  "kap": {
    "reading": "(カ)↑プ",
    "meaning": "私",
    "etymology": "・ポケモン名 カプ・コケコなどから",
    "examples": [
      {
        "kapu": "kipos gu kap ga siali.",
        "japanese": "私はしゃりーです。"
      }
    ],
    "notes": "特になし"
  },
  "imalo": {
    "reading": "イ(マー)↑ロ",
    "meaning": "さようなら",
    "etymology": "・音象徴「悲しい」から",
    "examples": [
      {
        "kapu": "imalo e siali.",
        "japanese": "さようなら、しゃりー。"
      }
    ],
    "notes": "特になし"
  },
  "e": {
    "reading": "エ",
    "meaning": "[e ~で] ~へ、~に向けて",
    "etymology": "・ハワイ語より",
    "examples": [
      {
        "kapu": "neban gu kap ga nialo e siali.",
        "japanese": "私はしゃりーにおはようと言う。"
      },
      {
        "kapu": "e malil si, alola!",
        "japanese": "マリルさん、こんにちは！"
      }
    ],
    "notes": "alola e siali! などのように、eの後に名詞が続く。<br>あいさつなど、一部の状況では文頭にeを付けることができる。"
  },
  "si": {
    "reading": "(シ)↓",
    "meaning": "[~ siで] ~さん",
    "etymology": "・日本語「~氏」より<br>・韓国語「~씨」より",
    "examples": [
      {
        "kapu": "e malil si, alola!",
        "japanese": "マリルさん、こんにちは！"
      }
    ],
    "notes": "siの前には通常、人の名前が来る。"
  },
  "nialo": {
    "reading": "(ニャー)↑ロ",
    "meaning": "おはよう(起きた時)",
    "etymology": "・音象徴「猫の鳴き声」から<br>・朝、猫が飼い主を起こしにくることから",
    "examples": [
      {
        "kapu": "neban gu kap ga nialo e siali.",
        "japanese": "私はしゃりーにおはようと言う。"
      }
    ],
    "notes": "街中などで、朝に挨拶をするときはohukを使う。<br>nialoは、おやすみの朝バージョンとして考えるとよい。"
  },
  "mioat": {
    "reading": "(ミョー)↑アッ",
    "meaning": "おやすみ",
    "etymology": "・音象徴「やわらかい」から<br>・ふかふかのベッドで寝ることから",
    "examples": [
      {
        "kapu": "neban gu kiopa ga mioat.",
        "japanese": "守り神はおやすみと言う。"
      }
    ],
    "notes": "特になし"
  },
  "ohuk": {
    "reading": "(オー)↑フック",
    "meaning": "おはよう(街中などで)",
    "etymology": "よくわからない。<br>・日本語「おはよう」から？",
    "examples": [
      {
        "kapu": "kopis gu kap ga ohuk.",
        "japanese": "私はおはよう(という言葉)が好き。"
      }
    ],
    "notes": "朝目覚めたときには、nialoを使う。<br>ohukは、こんばんはの朝バージョンとして考えるとよい。"
  },
  "solk": {
    "reading": "(ソー)↑ルク",
    "meaning": "こんばんは",
    "etymology": "よくわからない。<br>・音象徴「だんだんと」から？<br>・月が昇る様子から？",
    "examples": [
      {
        "kapu": "neban gu liun ga solk",
        "japanese": "月がこんばんはと言う。"
      }
    ],
    "notes": "特になし"
  },
  "zolia": {
    "reading": "(ゾー)↑リャ",
    "meaning": "失礼します、すみません",
    "etymology": "・なんとなく？",
    "examples": [
      {
        "kapu": "e siali si, zolia.",
        "japanese": "しゃりーさん、すみません。"
      }
    ],
    "notes": "特になし"
  },
  "malalo": {
    "reading": "マ(ラー)↑ロ",
    "meaning": "ありがとう",
    "etymology": "・ハワイ語「mahalo」より",
    "examples": [
      {
        "kapu": "malalo e kiopa.",
        "japanese": "ありがとう、守り神よ。"
      }
    ],
    "notes": "特になし"
  },
  "kalam": {
    "reading": "カーラム",
    "meaning": "ごめんなさい",
    "etymology": "・なんとなく？",
    "examples": [
      {
        "kapu": "ma, kalam.",
        "japanese": "うーん、ごめん。"
      }
    ],
    "notes": "特になし"
  },
  "siuba": {
    "reading": "(シュバー)↑",
    "meaning": "すごい",
    "etymology": "・日本語「すばらしい」から",
    "examples": [
      {
        "kapu": "mu, e leh, siuba.",
        "japanese": "いや、あなたはすごい。"
      }
    ],
    "notes": "感動詞としての使い方。<br>日本語の「すごい量」などのすごいとは違う。"
  },
  "ne": {
    "reading": "ネ",
    "meaning": "はい、うん",
    "etymology": "・韓国語「네」から",
    "examples": [
      {
        "kapu": "ne, siabuz",
        "japanese": "はい、元気です。"
      }
    ],
    "notes": "naと混同しないように注意。"
  },
  "mu": {
    "reading": "ム",
    "meaning": "いいえ、いや",
    "etymology": "・日本語「無」から",
    "examples": [
      {
        "kapu": "mu, e leh, siuba.",
        "japanese": "いや、あなたはすごい。"
      }
    ],
    "notes": "maと混同しないように注意。"
  },
  "na": {
    "reading": "ナ",
    "meaning": "いいね",
    "etymology": "・kap語「ne」(はい)から。",
    "examples": [
      {
        "kapu": "na, sa gu kap!",
        "japanese": "いいね、私、やる！"
      }
    ],
    "notes": "neと混同しないように注意。"
  },
  "ma": {
    "reading": "マ",
    "meaning": "うーん",
    "etymology": "・kap語「ma」(いいえ)から",
    "examples": [
      {
        "kapu": "ma, kalam.",
        "japanese": "うーん、ごめん。"
      }
    ],
    "notes": "muより弱い否定である。"
  },
  "kipos": {
    "reading": "キ(ポー)↑ス",
    "meaning": "[存在動詞] (ga ~) である",
    "etymology": "・kap(私) + s(動詞化する)から",
    "examples": [
      {
        "kapu": "kipos gu kap ga siali.",
        "japanese": "私はしゃりーだ。"
      }
    ],
    "notes": "kiposを使った文は、gu = gaの関係になる。"
  },
  "sa": {
    "reading": "サー",
    "meaning": "(ga ~) をする",
    "etymology": "・日本語「する」から",
    "examples": [
      {
        "kapu": "na!, sa gu kap zak ga nia!",
        "japanese": "いいね！私達はあれをするよ！"
      }
    ],
    "notes": "特になし"
  },
  "kopis": {
    "reading": "(コ)↑ピス",
    "meaning": "(ga ~) が好き",
    "etymology": "・kap(私) + s(動詞化する)から",
    "examples": [
      {
        "kapu": "kopis gu kap ga susi.",
        "japanese": "私は寿司が好きです。"
      }
    ],
    "notes": "特になし"
  },
  "mukopis": {
    "reading": "(ム)↓コピス",
    "meaning": "(ga ~) が嫌い",
    "etymology": "・mu(否定) + kopis(好き)から",
    "examples": [
      {
        "kapu": "mukopis gu kap ga kikiok.",
        "japanese": "私は人が嫌いだ。"
      }
    ],
    "notes": "特になし"
  },
  "basiu": {
    "reading": "(バ)↑シュ",
    "meaning": "(ga ~) を攻撃する",
    "etymology": "・音象徴「切る」から",
    "examples": [
      {
        "kapu": "basiu mutia gu kiopa ga kikiok zak.",
        "japanese": "守り神は人を攻撃しない。"
      }
    ],
    "notes": "特になし"
  },
  "susian": {
    "reading": "(スー)↑シャン",
    "meaning": "(ga ~) を守る",
    "etymology": "・なんとなく？<br>kap語「basiu」から？",
    "examples": [
      {
        "kapu": "susian gu kiopa ga mikug zak.",
        "japanese": "守り神は島を守る。"
      }
    ],
    "notes": "特になし"
  },
  "neban": {
    "reading": "(ネ)↑バン",
    "meaning": "(ga ~) について話す、(ga ~) と言う",
    "etymology": "・kap語「nabon」(虫)から<br>・虫はたくさん話してそうだから",
    "examples": [
      {
        "kapu": "neban gu kap ga piki e siali.",
        "japanese": "私はしゃりーに明日について話す。"
      },
      {
        "kapu": "neban gu kiopa ga mioat.",
        "japanese": "守り神はおやすみと言う。"
      }
    ],
    "notes": "特になし"
  },
  "lopun": {
    "reading": "(ロ)↑プン",
    "meaning": "(ga ~) に行く",
    "etymology": "kap語「lapon」(飛行)から<br>・飛行できるならいろんな場所に行けそうだから",
    "examples": [
      {
        "kapu": "lopun gu kap ga hual.",
        "japanese": "私は家に行く。"
      }
    ],
    "notes": "特になし"
  },
  "biopet": {
    "reading": "(ビョー)↑ペット",
    "meaning": "(ga ~) を聞く",
    "etymology": "・kap語「bapot」(エスパー)から<br>・いろいろな物の声が聞こえそうだから",
    "examples": [
      {
        "kapu": "gan gu kap zank biopet ga imalo",
        "japanese": "私はさようならと聞くと悲しくなる。"
      }
    ],
    "notes": "特になし"
  },
  "kalom": {
    "reading": "(カー)↑ロム",
    "meaning": "(ga ~) を書く、(ga ~) について書く",
    "etymology": "・なんとなく?<br>・たぶん「kalam」(ごめん)とは関係ない",
    "examples": [
      {
        "kapu": "kalom gu kap ga mikupal e siali.",
        "japanese": "私はしゃりーのために地図を書く。"
      },
      {
        "kapu": "kalom gu kap ga mohu.",
        "japanese": "私は昨日について書く。"
      }
    ],
    "notes": "特になし"
  },
  "ziat": {
    "reading": "(ジャ)↑ット",
    "meaning": "(ga ~) を見る",
    "etymology": "・日本語「じーっと」から",
    "examples": [
      {
        "kapu": "ziat gu ton ga kap.",
        "japanese": "彼は私を見る。"
      }
    ],
    "notes": "特になし"
  },
  "gasia": {
    "reading": "(グァー)↑シャ",
    "meaning": "(ga ~) を作る",
    "etymology": "・日本語「ガチャガチャと」から<br>・すごい物を作るのは大きな音がでるから。",
    "examples": [
      {
        "kapu": "gasia gu kap ga musia.",
        "japanese": "私は食べ物を作る。"
      }
    ],
    "notes": "特になし"
  },
  "pona": {
    "reading": "(ポー)↑ナ",
    "meaning": "(ga ~) を手に入れる",
    "etymology": "・効果音「ポン」から<br>・ゲームなどで物を拾ったときの音。",
    "examples": [
      {
        "kapu": "pona gu kikiok zak ga hagoz.",
        "japanese": "人々は火を手に入れる。"
      }
    ],
    "notes": "特になし"
  },
  "ziasa": {
    "reading": "(ジャー)↑サ",
    "meaning": "(ga ~) が欲しい",
    "etymology": "・なんとなく?",
    "examples": [
      {
        "kapu": "ziasa gu kap ga palal.",
        "japanese": "私は本が欲しい。"
      }
    ],
    "notes": "特になし"
  },
  "kapas":  {
    "reading": "(カ)↑パス",
    "meaning": "強い",
    "etymology": "・kap(私)から<br>・カプ神は強いよ！",
    "examples": [
      {
        "kapu": "golazat gu zakap la kapas",
        "japanese": "強いポケモンは大きい。"
      },
      {
        "kapu": "kapazat gu ton e zakap",
        "japanese": "彼はポケモンに対して強いよね"
      }
    ],
    "notes": ""
  }
}